{
    "commit_hash": "91052233cadc6f9fd3f0a59a02c807d1b5cb814f", 
    "date": 1527792582000, 
    "ended_at": {
        "henselizations.Rational.time_create": 1527794294000, 
        "splitting_fields.SplittingField.time_12_384": 1527795813000
    }, 
    "env_name": "sage-py_home_sage_sage_local_bin_python", 
    "params": {
        "arch": "x86_64", 
        "cpu": "Intel(R) Xeon(R) CPU E5-2680 v2 @ 2.80GHz or similar", 
        "machine": "CircleCI", 
        "os": "Linux", 
        "python": "2.7", 
        "ram": "61830880"
    }, 
    "profiles": {}, 
    "python": "2.7", 
    "requirements": {}, 
    "results": {
        "henselizations.Rational.time_create": 4.9976395400000004e-05, 
        "splitting_fields.SplittingField.time_12_384": 1516.357699015
    }, 
    "started_at": {
        "henselizations.Rational.time_create": 1527794290000, 
        "splitting_fields.SplittingField.time_12_384": 1527794294000
    }, 
    "version": 1
}